{
    "testimonials": [
        {
            "id": 1,
            "name": "John",
            "surname": "Doe",
            "review": "The food at this restaurant is exceptional! I loved every dish I tried. The ambiance was cozy, and the staff was friendly and attentive."
        },
        {
            "id": 2,
            "name": "Alice",
            "surname": "Smith",
            "review": "I had an amazing dining experience here! The flavors in each dish were exquisite, and the presentation was beautiful. I can't wait to come back!"
        },
        {
            "id": 3,
            "name": "Michael",
            "surname": "Johnson",
            "review": "This restaurant exceeded all my expectations! The service was impeccable, and the food was simply delicious. I highly recommend it to everyone!"
        },
        {
            "id": 4,
            "name": "Emily",
            "surname": "Brown",
            "review": "Absolutely fantastic! The atmosphere was charming, and the food was divine. I thoroughly enjoyed every moment of my meal here."
        },
        {
            "id": 5,
            "name": "David",
            "surname": "Wilson",
            "review": "An outstanding dining experience! The dishes were creative and flavorful, and the staff was incredibly attentive. I'll definitely be returning!"
        }
    ]
}